coopdevsutils.py
bi_coopdevs_utils-0.0.2.dist-info/METADATA
bi_coopdevs_utils-0.0.2.dist-info/WHEEL
bi_coopdevs_utils-0.0.2.dist-info/top_level.txt
bi_coopdevs_utils-0.0.2.dist-info/RECORD
