Metadata-Version: 2.1
Name: bi-coopdevs-utils
Version: 0.0.2
Summary: Util functions for BI
Author: Coopdevs
Author-email: info@coopdevs.org
Classifier: Programming Language :: Python :: 3
Classifier: Operating System :: OS Independent
Requires-Python: >=3.6
